32-Bit Harware Devider Design/HD32/HD32.v
// HD32.v

`define InputWidth 32
`define OutputWidth 32

module HD32(
    input mode, // determine the unsigned/signed division
    input [`InputWidth-1:0] dividend,
    input [`InputWidth-1:0] divider,
    output reg [`OutputWidth-1:0] quotient,
    output reg [`OutputWidth-1:0] remainder,
    output reg zero_error // if divider==0
);

reg [`InputWidth-1:0] msb_dividend; // the first "1" in dividend
reg [`InputWidth-1:0] msb_divider;  // the first "1" in divider
reg [`InputWidth-1:0] reg_dividend,temp_dividend;  
reg [`InputWidth-1:0] reg_divider,temp_divider;  
integer i; // used for shifting bits 

// convert to positive values 
// determine the msb of 1
always @(*) begin
    if (mode==0) begin // unsigned division
        reg_dividend=dividend;
        reg_divider=divider;
    end
    else begin // signed
        // if negative
        reg_dividend=dividend[`InputWidth-1]==1?~dividend[`InputWidth-1:0]+1:dividend;
        reg_divider=divider[`InputWidth-1]==1?~divider[`InputWidth-1:0]+1:divider;
    end
    msb_dividend=msb(reg_dividend);
    msb_divider=msb(reg_divider);
end

// perform division
always @(*) begin
    zero_error=0;
    // divider==0
    if (reg_divider==0) begin
        quotient=`OutputWidth'b0;
        remainder=`OutputWidth'b0;
        zero_error=1;
    end
    // compare two operands
    // dividend<divider?
    else if (reg_dividend<reg_divider) begin
        quotient=`OutputWidth'b0;
        remainder=reg_dividend;
    end
    // dividend>=divider
    else begin 
        quotient=`OutputWidth'b0;
        remainder=reg_dividend;
        temp_divider=reg_divider<<(msb_dividend-msb_divider); // variational subtrahend
        for(i=msb_dividend-msb_divider;i>=0;i=i-1) begin
            quotient=quotient<<1;
            if (remainder>=temp_divider) begin
                remainder=remainder-temp_divider;
                quotient[0]=1;
            end
            else 
                quotient[0]=0;
            temp_divider=temp_divider>>1;
        end
    end
    // convert back to correct number
    if (mode==1 && dividend[`InputWidth-1]^divider[`InputWidth-1]) // neg
        quotient[`OutputWidth-1:0]=~quotient[`OutputWidth-1:0]+1;
    if (mode==1 && dividend[`InputWidth-1])
    remainder[`OutputWidth-1:0]=~remainder[`OutputWidth-1:0]+1;
end


// function, determine msb for 1
function [`InputWidth-1:0] msb;
input [`InputWidth-1:0] in;
integer i; // iteration variable
begin
    for(i=`InputWidth-1;i>=0;i=i-1) begin
    if (in[i]==1) begin
    msb=i;
    i=0;
    end
end
end
endfunction

endmodule

32-Bit Harware Devider Design/HD32/testbench.v
// testbench.v

`define InputWidth 32
`define OutputWidth 32
`include "HD32.v"

module testbench;
// input
reg i_mode;
reg[`InputWidth-1:0] i_dividend;
reg[`InputWidth-1:0] i_divider;
// output
wire[`OutputWidth-1:0] o_quotient;
wire[`OutputWidth-1:0] o_remainder;
wire o_zero_error;

reg [7:0] delay=10; // for test

// DUT
HD32 HD32(i_mode,i_dividend,i_divider,o_quotient,o_remainder,o_zero_error);

//
initial begin
    $dumpfile("HD32.vcd");
    $dumpvars;
    $dumpon;
    #1000 $dumpoff;
    $dumpall;
end

// monitor
initial
begin
    $monitor("At time=%d\nmode=%b\ndividend=%b\ndivider=%b\nquotient=%b\nremainder=%b\no_zero_error=%b\n",
    $time,i_mode,i_dividend,i_divider,o_quotient,o_remainder,o_zero_error);
end

// test
initial
begin
    // unsigned
    #delay;
    i_mode=0;
    i_dividend=`InputWidth'b01100000; // 96
    i_divider=`InputWidth'b1100; // 12
    #delay;
    i_divider=`InputWidth'b1101; // 13
    #delay;
    i_divider=`InputWidth'b01100000; // 0
    #delay;
    i_divider=`InputWidth'b01100010; // 98
    #delay;
    i_dividend=`InputWidth'b0; // 0
    #delay;
    i_dividend=`InputWidth'b11111111_11111111_11111111_11111111; // the largest positive number
    #delay;
    i_divider=`InputWidth'b0; // 0
    // signed
    #delay;
    i_mode=1;
    i_dividend=`InputWidth'b01100000; // 96
    i_divider=`InputWidth'b1100; // 12
    #delay;
    i_divider=`InputWidth'b1101; // 13
    #delay;
    i_divider=`InputWidth'b01100000; // 0
    #delay;
    i_divider=`InputWidth'b01100010; // 98
    #delay;
    i_dividend=`InputWidth'b0; // 0
    #delay;
    i_dividend=`InputWidth'b11111111_11111111_11111111_10100000; // -96
    i_divider=`InputWidth'b1100; // 12
    #delay;
    i_divider=`InputWidth'b1101; // 13
    #delay;
    i_divider=`InputWidth'b01100010; // 98
    #delay;
    i_dividend=`InputWidth'b01100000; // 96
    i_divider=`InputWidth'b11111111111111111111111111110100; // -12
    #delay;
    i_divider=`InputWidth'b11111111111111111111111111110011; // -13
    #delay;
    i_divider=`InputWidth'b11111111_11111111_11111111_10100000; // -96
    #delay;
    i_divider=`InputWidth'b11111111111111111111111110011110; // -98
    #delay;
    i_divider=`InputWidth'b11111111_11111111_11111111_11111111; // -1
    #delay;
    i_dividend=`InputWidth'b11111111_11111111_11111111_10100000; // -96
    i_divider=`InputWidth'b11111111111111111111111111110100; // -12
    #delay;
    i_divider=`InputWidth'b11111111111111111111111111110011; // -13
    #delay;
    i_divider=`InputWidth'b11111111_11111111_11111111_10100000; // -96
    #delay;
    i_divider=`InputWidth'b11111111111111111111111110011110; // -98
    #delay;
    i_dividend=`InputWidth'b01111111_11111111_11111111_11111111; // the smallest negative number
    #delay;
    i_dividend=`InputWidth'b11111111_11111111_11111111_11111111; // -1
    #delay;
    i_dividend=`InputWidth'b0; // 0
    #delay;
    i_divider=`InputWidth'b0; // 0
end

endmodule

32-Bit Harware Devider Design/HD32/HD32.vcd
$date
	Mon Nov  2 01:11:45 2020
$end

$version
	Synopsys VCS version G-2012.09
$end

$timescale
	1s
$end

$comment Csum: 1 4d5d1c0e0bb2a15e $end


$scope module testbench $end
$var reg 1 ! i_mode $end
$var reg 32 " i_dividend [31:0] $end
$var reg 32 # i_divider [31:0] $end
$var wire 32 $ o_quotient [31:0] $end
$var wire 32 % o_remainder [31:0] $end
$var wire 1 & o_zero_error $end
$var reg 8 ' delay [7:0] $end

$scope module HD32 $end
$var wire 1 ! mode $end
$var wire 32 " dividend [31:0] $end
$var wire 32 # divider [31:0] $end
$var reg 32 ( quotient [31:0] $end
$var reg 32 ) remainder [31:0] $end
$var reg 1 * zero_error $end
$var reg 32 + msb_dividend [31:0] $end
$var reg 32 , msb_divider [31:0] $end
$var reg 32 - reg_dividend [31:0] $end
$var reg 32 . temp_dividend [31:0] $end
$var reg 32 / reg_divider [31:0] $end
$var reg 32 0 temp_divider [31:0] $end
$var integer 32 1 i $end

$scope function msb $end
$var reg 32 2 msb [31:0] $end
$var reg 32 3 in [31:0] $end
$var integer 32 4 i $end
$upscope $end

$upscope $end

$upscope $end

$enddefinitions $end

#0
$dumpvars
x!
x&
x*
b00001010 '
bxxxxxxxxxxxxxxxxxxxxxxxxxxxxxxxx 1
bxxxxxxxxxxxxxxxxxxxxxxxxxxxxxxxx "
bxxxxxxxxxxxxxxxxxxxxxxxxxxxxxxxx #
bxxxxxxxxxxxxxxxxxxxxxxxxxxxxxxxx 4
bxxxxxxxxxxxxxxxxxxxxxxxxxxxxxxxx 3
bxxxxxxxxxxxxxxxxxxxxxxxxxxxxxxxx 2
bxxxxxxxxxxxxxxxxxxxxxxxxxxxxxxxx +
bxxxxxxxxxxxxxxxxxxxxxxxxxxxxxxxx ,
bxxxxxxxxxxxxxxxxxxxxxxxxxxxxxxxx $
bxxxxxxxxxxxxxxxxxxxxxxxxxxxxxxxx %
bxxxxxxxxxxxxxxxxxxxxxxxxxxxxxxxx (
bxxxxxxxxxxxxxxxxxxxxxxxxxxxxxxxx -
bxxxxxxxxxxxxxxxxxxxxxxxxxxxxxxxx /
bxxxxxxxxxxxxxxxxxxxxxxxxxxxxxxxx )
bxxxxxxxxxxxxxxxxxxxxxxxxxxxxxxxx .
bxxxxxxxxxxxxxxxxxxxxxxxxxxxxxxxx 0
$end
$dumpon
x!
x&
x*
b00001010 '
bxxxxxxxxxxxxxxxxxxxxxxxxxxxxxxxx 1
bxxxxxxxxxxxxxxxxxxxxxxxxxxxxxxxx "
bxxxxxxxxxxxxxxxxxxxxxxxxxxxxxxxx #
bxxxxxxxxxxxxxxxxxxxxxxxxxxxxxxxx 4
bxxxxxxxxxxxxxxxxxxxxxxxxxxxxxxxx 3
bxxxxxxxxxxxxxxxxxxxxxxxxxxxxxxxx 2
bxxxxxxxxxxxxxxxxxxxxxxxxxxxxxxxx +
bxxxxxxxxxxxxxxxxxxxxxxxxxxxxxxxx ,
bxxxxxxxxxxxxxxxxxxxxxxxxxxxxxxxx $
bxxxxxxxxxxxxxxxxxxxxxxxxxxxxxxxx %
bxxxxxxxxxxxxxxxxxxxxxxxxxxxxxxxx (
bxxxxxxxxxxxxxxxxxxxxxxxxxxxxxxxx -
bxxxxxxxxxxxxxxxxxxxxxxxxxxxxxxxx /
bxxxxxxxxxxxxxxxxxxxxxxxxxxxxxxxx )
bxxxxxxxxxxxxxxxxxxxxxxxxxxxxxxxx .
bxxxxxxxxxxxxxxxxxxxxxxxxxxxxxxxx 0
$end
#10
0!
b00000000000000000000000001100000 "
b00000000000000000000000000001100 #
b00000000000000000000000000000011 ,
b00000000000000000000000000000110 +
b00000000000000000000000000000011 2
b11111111111111111111111111111111 4
b00000000000000000000000000001100 3
b00000000000000000000000000001100 /
b00000000000000000000000001100000 -
0*
0&
b11111111111111111111111111111111 1
b00000000000000000000000000000110 0
b00000000000000000000000000001000 (
b00000000000000000000000000001000 $
b00000000000000000000000000000000 )
b00000000000000000000000000000000 %
#20
b00000000000000000000000000001101 #
b00000000000000000000000000001101 3
b00000000000000000000000000001101 /
b00000000000000000000000000000101 )
b00000000000000000000000000000101 %
b00000000000000000000000000000111 (
b00000000000000000000000000000111 $
#30
b00000000000000000000000001100000 #
b00000000000000000000000000000110 ,
b00000000000000000000000000000110 2
b00000000000000000000000001100000 3
b00000000000000000000000001100000 /
b00000000000000000000000000110000 0
b00000000000000000000000000000001 (
b00000000000000000000000000000001 $
b00000000000000000000000000000000 )
b00000000000000000000000000000000 %
#40
b00000000000000000000000001100010 #
b00000000000000000000000001100010 3
b00000000000000000000000001100010 /
b00000000000000000000000001100000 )
b00000000000000000000000001100000 %
b00000000000000000000000000000000 (
b00000000000000000000000000000000 $
#50
b00000000000000000000000000000000 "
b00000000000000000000000000000000 -
b00000000000000000000000000000000 )
b00000000000000000000000000000000 %
#60
b11111111111111111111111111111111 "
b00000000000000000000000000011111 +
b11111111111111111111111111111111 -
b00000000000000000000000000110001 0
b00000010100111001011110000010100 (
b00000010100111001011110000010100 $
b00000000000000000000000001010111 )
b00000000000000000000000001010111 %
#70
b00000000000000000000000000000000 #
b00000000000000000000000000011111 ,
b00000000000000000000000000011111 2
b00000000000000000000000000000000 3
b00000000000000000000000000000000 /
1*
1&
b00000000000000000000000000000000 )
b00000000000000000000000000000000 %
b00000000000000000000000000000000 (
b00000000000000000000000000000000 $
#80
1!
b00000000000000000000000001100000 "
b00000000000000000000000000001100 #
b00000000000000000000000000000011 ,
b00000000000000000000000000000110 +
b00000000000000000000000000000011 2
b00000000000000000000000000001100 3
b00000000000000000000000000001100 /
b00000000000000000000000001100000 -
0*
0&
b00000000000000000000000000000110 0
b00000000000000000000000000001000 (
b00000000000000000000000000001000 $
#90
b00000000000000000000000000001101 #
b00000000000000000000000000001101 3
b00000000000000000000000000001101 /
b00000000000000000000000000000101 )
b00000000000000000000000000000101 %
b00000000000000000000000000000111 (
b00000000000000000000000000000111 $
#100
b00000000000000000000000001100000 #
b00000000000000000000000000000110 ,
b00000000000000000000000000000110 2
b00000000000000000000000001100000 3
b00000000000000000000000001100000 /
b00000000000000000000000000110000 0
b00000000000000000000000000000001 (
b00000000000000000000000000000001 $
b00000000000000000000000000000000 )
b00000000000000000000000000000000 %
#110
b00000000000000000000000001100010 #
b00000000000000000000000001100010 3
b00000000000000000000000001100010 /
b00000000000000000000000001100000 )
b00000000000000000000000001100000 %
b00000000000000000000000000000000 (
b00000000000000000000000000000000 $
#120
b00000000000000000000000000000000 "
b00000000000000000000000000000000 -
b00000000000000000000000000000000 )
b00000000000000000000000000000000 %
#130
b11111111111111111111111110100000 "
b00000000000000000000000000001100 #
b00000000000000000000000000000011 ,
b00000000000000000000000000000011 2
b00000000000000000000000000001100 3
b00000000000000000000000000001100 /
b00000000000000000000000001100000 -
b00000000000000000000000000000110 0
b11111111111111111111111111111000 (
b11111111111111111111111111111000 $
#140
b00000000000000000000000000001101 #
b00000000000000000000000000001101 3
b00000000000000000000000000001101 /
b11111111111111111111111111111011 )
b11111111111111111111111111111011 %
b11111111111111111111111111111001 (
b11111111111111111111111111111001 $
#150
b00000000000000000000000001100010 #
b00000000000000000000000000000110 ,
b00000000000000000000000000000110 2
b00000000000000000000000001100010 3
b00000000000000000000000001100010 /
b11111111111111111111111110100000 )
b11111111111111111111111110100000 %
b00000000000000000000000000000000 (
b00000000000000000000000000000000 $
#160
b00000000000000000000000001100000 "
b11111111111111111111111111110100 #
b00000000000000000000000001100000 )
b00000000000000000000000001100000 %
b00000000000000000000000000000011 ,
b00000000000000000000000000000011 2
b00000000000000000000000000001100 3
b00000000000000000000000000001100 /
b11111111111111111111111111111000 (
b11111111111111111111111111111000 $
b00000000000000000000000000000000 )
b00000000000000000000000000000000 %
#170
b11111111111111111111111111110011 #
b00000000000000000000000000001101 3
b00000000000000000000000000001101 /
b00000000000000000000000000000101 )
b00000000000000000000000000000101 %
b11111111111111111111111111111001 (
b11111111111111111111111111111001 $
#180
b11111111111111111111111110100000 #
b00000000000000000000000000000110 ,
b00000000000000000000000000000110 2
b00000000000000000000000001100000 3
b00000000000000000000000001100000 /
b00000000000000000000000000110000 0
b11111111111111111111111111111111 (
b11111111111111111111111111111111 $
b00000000000000000000000000000000 )
b00000000000000000000000000000000 %
#190
b11111111111111111111111110011110 #
b00000000000000000000000001100010 3
b00000000000000000000000001100010 /
b00000000000000000000000001100000 )
b00000000000000000000000001100000 %
b00000000000000000000000000000000 (
b00000000000000000000000000000000 $
#200
b11111111111111111111111111111111 #
b00000000000000000000000000000000 ,
b00000000000000000000000000000000 2
b00000000000000000000000000000001 3
b00000000000000000000000000000001 /
b00000000000000000000000000000000 0
b11111111111111111111111110100000 (
b11111111111111111111111110100000 $
b00000000000000000000000000000000 )
b00000000000000000000000000000000 %
#210
b11111111111111111111111110100000 "
b11111111111111111111111111110100 #
b00000000000000000000000001100000 (
b00000000000000000000000001100000 $
b00000000000000000000000000000011 ,
b00000000000000000000000000000011 2
b00000000000000000000000000001100 3
b00000000000000000000000000001100 /
b00000000000000000000000000000110 0
b00000000000000000000000000001000 (
b00000000000000000000000000001000 $
#220
b11111111111111111111111111110011 #
b00000000000000000000000000001101 3
b00000000000000000000000000001101 /
b11111111111111111111111111111011 )
b11111111111111111111111111111011 %
b00000000000000000000000000000111 (
b00000000000000000000000000000111 $
#230
b11111111111111111111111110100000 #
b00000000000000000000000000000110 ,
b00000000000000000000000000000110 2
b00000000000000000000000001100000 3
b00000000000000000000000001100000 /
b00000000000000000000000000110000 0
b00000000000000000000000000000001 (
b00000000000000000000000000000001 $
b00000000000000000000000000000000 )
b00000000000000000000000000000000 %
#240
b11111111111111111111111110011110 #
b00000000000000000000000001100010 3
b00000000000000000000000001100010 /
b11111111111111111111111110100000 )
b11111111111111111111111110100000 %
b00000000000000000000000000000000 (
b00000000000000000000000000000000 $
#250
b01111111111111111111111111111111 "
b00000000000000000000000001100000 )
b00000000000000000000000001100000 %
b00000000000000000000000000011110 +
b01111111111111111111111111111111 -
b00000000000000000000000000110001 0
b11111110101100011010000111110110 (
b11111110101100011010000111110110 $
b00000000000000000000000000101011 )
b00000000000000000000000000101011 %
#260
b11111111111111111111111111111111 "
b00000001010011100101111000001010 (
b00000001010011100101111000001010 $
b11111111111111111111111111010101 )
b11111111111111111111111111010101 %
b00000000000000000000000000000000 +
b00000000000000000000000000000001 -
b11111111111111111111111111111111 )
b11111111111111111111111111111111 %
b00000000000000000000000000000000 (
b00000000000000000000000000000000 $
#270
b00000000000000000000000000000000 "
b00000000000000000000000000000001 )
b00000000000000000000000000000001 %
b00000000000000000000000000000110 +
b00000000000000000000000000000000 -
b00000000000000000000000000000000 )
b00000000000000000000000000000000 %
#280
b00000000000000000000000000000000 #
b00000000000000000000000000000000 3
b00000000000000000000000000000000 /
1*
1&
#1000
$dumpall
1!
1&
1*
b00001010 '
b11111111111111111111111111111111 1
b00000000000000000000000000000000 "
b00000000000000000000000000000000 #
b11111111111111111111111111111111 4
b00000000000000000000000000000000 3
b00000000000000000000000000000110 2
b00000000000000000000000000000110 +
b00000000000000000000000000000110 ,
b00000000000000000000000000000000 $
b00000000000000000000000000000000 %
b00000000000000000000000000000000 (
b00000000000000000000000000000000 -
b00000000000000000000000000000000 /
b00000000000000000000000000000000 )
bxxxxxxxxxxxxxxxxxxxxxxxxxxxxxxxx .
b00000000000000000000000000110001 0
$end
$dumpoff
x!
x&
x*
bxxxxxxxx '
bxxxxxxxxxxxxxxxxxxxxxxxxxxxxxxxx 1
bxxxxxxxxxxxxxxxxxxxxxxxxxxxxxxxx "
bxxxxxxxxxxxxxxxxxxxxxxxxxxxxxxxx #
bxxxxxxxxxxxxxxxxxxxxxxxxxxxxxxxx 4
bxxxxxxxxxxxxxxxxxxxxxxxxxxxxxxxx 3
bxxxxxxxxxxxxxxxxxxxxxxxxxxxxxxxx 2
bxxxxxxxxxxxxxxxxxxxxxxxxxxxxxxxx +
bxxxxxxxxxxxxxxxxxxxxxxxxxxxxxxxx ,
bxxxxxxxxxxxxxxxxxxxxxxxxxxxxxxxx $
bxxxxxxxxxxxxxxxxxxxxxxxxxxxxxxxx %
bxxxxxxxxxxxxxxxxxxxxxxxxxxxxxxxx (
bxxxxxxxxxxxxxxxxxxxxxxxxxxxxxxxx -
bxxxxxxxxxxxxxxxxxxxxxxxxxxxxxxxx /
bxxxxxxxxxxxxxxxxxxxxxxxxxxxxxxxx )
bxxxxxxxxxxxxxxxxxxxxxxxxxxxxxxxx .
bxxxxxxxxxxxxxxxxxxxxxxxxxxxxxxxx 0
$end
